courseragoogleitautomationwithpython/__init__.py
courseragoogleitautomationwithpython/courses/__init__.py
courseragoogleitautomationwithpython/courses/automatingrealworldtaskswithpython/__init__.py
courseragoogleitautomationwithpython/courses/configurationmanagementandthecloud/__init__.py
courseragoogleitautomationwithpython/courses/crashcourseonpython/__init__.py
courseragoogleitautomationwithpython/courses/crashcourseonpython/week1/__init__.py
courseragoogleitautomationwithpython/courses/crashcourseonpython/week1/modulequiz.md
courseragoogleitautomationwithpython/courses/crashcourseonpython/week1/practicequizhelloword.md
courseragoogleitautomationwithpython/courses/crashcourseonpython/week1/practicequizintroductiontopython.md
courseragoogleitautomationwithpython/courses/crashcourseonpython/week2/__init__.py
courseragoogleitautomationwithpython/courses/crashcourseonpython/week2/modulequiz.md
courseragoogleitautomationwithpython/courses/crashcourseonpython/week2/practicequizconditionals.md
courseragoogleitautomationwithpython/courses/crashcourseonpython/week2/practicequizexpressionsandvariables.md
courseragoogleitautomationwithpython/courses/crashcourseonpython/week2/practicequizfunctions.md
courseragoogleitautomationwithpython/courses/crashcourseonpython/week3/__init__.py
courseragoogleitautomationwithpython/courses/crashcourseonpython/week3/modulequiz.md
courseragoogleitautomationwithpython/courses/crashcourseonpython/week3/practicequizforloops.md
courseragoogleitautomationwithpython/courses/crashcourseonpython/week3/practicequizrecursion.md
courseragoogleitautomationwithpython/courses/crashcourseonpython/week3/practicequizwhile.md
courseragoogleitautomationwithpython/courses/crashcourseonpython/week4/__init__.py
courseragoogleitautomationwithpython/courses/crashcourseonpython/week4/modulequiz.md
courseragoogleitautomationwithpython/courses/crashcourseonpython/week4/practicequizdictionaries.md
courseragoogleitautomationwithpython-1.0.0.dist-info/METADATA
courseragoogleitautomationwithpython-1.0.0.dist-info/WHEEL
courseragoogleitautomationwithpython-1.0.0.dist-info/RECORD
