Metadata-Version: 2.1
Name: courseragoogleitautomationwithpython
Version: 1.0.0
Summary: Coursera Google IT Automation With Python Professional Certificate
License: MIT
Author: ivenpoker
Author-email: ivenpoker@gmail.com
Requires-Python: >=3.11,<4.0
Classifier: License :: OSI Approved :: MIT License
Classifier: Programming Language :: Python :: 3
Classifier: Programming Language :: Python :: 3.11
Requires-Dist: poetry (>=1.4.0,<2.0.0)
